rpl_pack/__init__.py
rpl_pack/flag.py
rpl_pack/plotting.py
rpl_pack/rpl.py
rpl_pack/rpl_exceptions.py
rpl_pack/rpl_types.py
rpl_pack/utils.py
rpl_pack/test/__init__.py
rpl_pack/test/test_flag.py
rpl_pack/test/test_rpl.py
rpl_pack/test/test_utils.py
rpl_pack-0.1.7.dist-info/METADATA
rpl_pack-0.1.7.dist-info/WHEEL
rpl_pack-0.1.7.dist-info/licenses/LICENSE
rpl_pack-0.1.7.dist-info/RECORD
