Metadata-Version: 2.1
Name: rpl_pack
Version: 0.1.7
Summary: The Official Rock Physics Lab Web Service API.
Author-email: Joe McNease <joemcnease11@gmail.com>
License: MIT License
License-File: LICENSE
Classifier: License :: OSI Approved :: MIT License
Classifier: Operating System :: OS Independent
Classifier: Programming Language :: Python :: 3
Requires-Python: >=3.7
